pygrpc/__init__.py
pygrpc-0.1.dist-info/METADATA
pygrpc-0.1.dist-info/WHEEL
pygrpc-0.1.dist-info/top_level.txt
pygrpc-0.1.dist-info/RECORD
