Metadata-Version: 2.1
Name: pygrpc
Version: 0.1
Summary: Python bindings for gRPC C++
Home-page: UNKNOWN
Author: Mehrdad Afshari
Author-email: mehrdad.afshari@gmail.com
License: UNKNOWN
Platform: UNKNOWN
